waft/__init__.py
waft/application.py
waft/authentication.py
waft/database.py
waft/datatypes.py
waft/keyring.py
waft/messages.py
waft/metadata.py
waft/model.py
waft/screens.py
waft/splashtext.txt
waft/spotify.py
waft/utils.py
waft/waft.py
waft/widgets.py
waft/youtube.py
waft/ytdlp.py
waft/styles/main.tcss
waft-0.1.9.dist-info/METADATA
waft-0.1.9.dist-info/WHEEL
waft-0.1.9.dist-info/entry_points.txt
waft-0.1.9.dist-info/RECORD
