Metadata-Version: 2.4
Name: waft
Version: 0.1.9
Summary: A textual user interface application that facilitates the association of files in the MP3 format with metadd.
Project-URL: Documentation, https://github.com/me11203sci/wiki-application-for-tunes/blob/master/README.md
Project-URL: Issues, https://github.com/me11203sci/wiki-application-for-tunes/issues
Project-URL: Source, https://github.com/me11203sci/wiki-application-for-tunes
Author-email: Melesio Albavera <ma6hv@umsystem.edu>
License-Expression: MIT
Classifier: Development Status :: 4 - Beta
Classifier: Programming Language :: Python
Classifier: Programming Language :: Python :: 3.8
Classifier: Programming Language :: Python :: 3.9
Classifier: Programming Language :: Python :: 3.10
Classifier: Programming Language :: Python :: 3.11
Classifier: Programming Language :: Python :: 3.12
Classifier: Programming Language :: Python :: Implementation :: CPython
Classifier: Programming Language :: Python :: Implementation :: PyPy
Requires-Python: >=3.8
Requires-Dist: eyed3
Requires-Dist: google-api-python-client
Requires-Dist: music-tag
Requires-Dist: pillow
Requires-Dist: pymongo
Requires-Dist: python-mpv
Requires-Dist: requests
Requires-Dist: securecredentials
Requires-Dist: textual
Requires-Dist: textual-dev
Requires-Dist: types-requests
Requires-Dist: types-yt-dlp
Requires-Dist: yt-dlp
